tensorrt_lean_libs/__init__.py
tensorrt_lean_libs/nvinfer_lean_10.dll
tensorrt_lean_libs/nvinfer_vc_plugin_10.dll
tensorrt_lean_cu12_libs-10.15.1.29.dist-info/LICENSE.txt
tensorrt_lean_cu12_libs-10.15.1.29.dist-info/METADATA
tensorrt_lean_cu12_libs-10.15.1.29.dist-info/WHEEL
tensorrt_lean_cu12_libs-10.15.1.29.dist-info/top_level.txt
tensorrt_lean_cu12_libs-10.15.1.29.dist-info/zip-safe
tensorrt_lean_cu12_libs-10.15.1.29.dist-info/RECORD
